lifx_emulator/__init__.py
lifx_emulator/__main__.py
lifx_emulator/constants.py
lifx_emulator/server.py
lifx_emulator/api/__init__.py
lifx_emulator/api/app.py
lifx_emulator/api/models.py
lifx_emulator/api/mappers/__init__.py
lifx_emulator/api/mappers/device_mapper.py
lifx_emulator/api/routers/__init__.py
lifx_emulator/api/routers/devices.py
lifx_emulator/api/routers/monitoring.py
lifx_emulator/api/routers/scenarios.py
lifx_emulator/api/services/__init__.py
lifx_emulator/api/services/device_service.py
lifx_emulator/api/templates/dashboard.html
lifx_emulator/devices/__init__.py
lifx_emulator/devices/device.py
lifx_emulator/devices/manager.py
lifx_emulator/devices/observers.py
lifx_emulator/devices/persistence.py
lifx_emulator/devices/state_restorer.py
lifx_emulator/devices/state_serializer.py
lifx_emulator/devices/states.py
lifx_emulator/factories/__init__.py
lifx_emulator/factories/builder.py
lifx_emulator/factories/default_config.py
lifx_emulator/factories/factory.py
lifx_emulator/factories/firmware_config.py
lifx_emulator/factories/serial_generator.py
lifx_emulator/handlers/__init__.py
lifx_emulator/handlers/base.py
lifx_emulator/handlers/device_handlers.py
lifx_emulator/handlers/light_handlers.py
lifx_emulator/handlers/multizone_handlers.py
lifx_emulator/handlers/registry.py
lifx_emulator/handlers/tile_handlers.py
lifx_emulator/products/__init__.py
lifx_emulator/products/generator.py
lifx_emulator/products/registry.py
lifx_emulator/products/specs.py
lifx_emulator/products/specs.yml
lifx_emulator/protocol/__init__.py
lifx_emulator/protocol/base.py
lifx_emulator/protocol/const.py
lifx_emulator/protocol/generator.py
lifx_emulator/protocol/header.py
lifx_emulator/protocol/packets.py
lifx_emulator/protocol/protocol_types.py
lifx_emulator/protocol/serializer.py
lifx_emulator/repositories/__init__.py
lifx_emulator/repositories/device_repository.py
lifx_emulator/repositories/storage_backend.py
lifx_emulator/scenarios/__init__.py
lifx_emulator/scenarios/manager.py
lifx_emulator-2.3.1.dist-info/METADATA
lifx_emulator-2.3.1.dist-info/WHEEL
lifx_emulator-2.3.1.dist-info/entry_points.txt
lifx_emulator-2.3.1.dist-info/licenses/LICENSE
lifx_emulator-2.3.1.dist-info/RECORD
