Metadata-Version: 2.4
Name: lifx-emulator
Version: 2.3.1
Summary: LIFX Emulator for testing LIFX LAN protocol libraries
Author-email: Avi Miller <me@dje.li>
Maintainer-email: Avi Miller <me@dje.li>
License-Expression: UPL-1.0
License-File: LICENSE
Classifier: Framework :: AsyncIO
Classifier: Framework :: Pytest
Classifier: Intended Audience :: Developers
Classifier: Natural Language :: English
Classifier: Operating System :: OS Independent
Classifier: Programming Language :: Python :: 3.11
Classifier: Programming Language :: Python :: 3.12
Classifier: Programming Language :: Python :: 3.13
Classifier: Programming Language :: Python :: 3.14
Classifier: Topic :: Software Development :: Libraries
Classifier: Topic :: Software Development :: Libraries :: Python Modules
Classifier: Typing :: Typed
Requires-Python: >=3.11
Requires-Dist: cyclopts>=4.2.0
Requires-Dist: fastapi>=0.115.0
Requires-Dist: pyyaml>=6.0.3
Requires-Dist: rich>=14.2.0
Requires-Dist: uvicorn>=0.34.0
